lawhead_extractor/__init__.py
lawhead_extractor/main.py
lawhead_extractor/prompts.py
lawhead_extractor-2025.12.21190602.dist-info/METADATA
lawhead_extractor-2025.12.21190602.dist-info/WHEEL
lawhead_extractor-2025.12.21190602.dist-info/top_level.txt
lawhead_extractor-2025.12.21190602.dist-info/RECORD
