Metadata-Version: 2.4
Name: lawhead-extractor
Version: 2025.12.21190602
Summary: lawhead-extractor parses legal headlines, extracting parties, claim type and outcome using an LLM with pattern matching for accuracy.
Author-email: lawhead-extractor <hi@eugene.plus>
License: MIT
Project-URL: Homepage, https://github.com/chigwell/lawhead-extractor
Requires-Python: >=3.9
Requires-Dist: langchain-llm7>=0.0.0
Requires-Dist: llmatch-messages>=0.0.0
Requires-Dist: langchain-core>=0.3.0
